pyiced/_pyiced.pyi
pyiced/css_color.py
pyiced/logo.png
pyiced/_pyiced.cpython-38-i386-linux-gnu.so
pyiced/py.typed
pyiced/__init__.py
pyiced/__init__.pyi
pyiced-0.3.0a7.dist-info/METADATA
pyiced-0.3.0a7.dist-info/top_level.txt
pyiced-0.3.0a7.dist-info/RECORD
pyiced-0.3.0a7.dist-info/WHEEL
pyiced-0.3.0a7.dist-info/LICENSE.md
