Metadata-Version: 2.1
Name: pyiced
Version: 0.3.0a7
Summary: Bindings for Iced, a cross-platform GUI library focused on simplicity. Inspired by Elm.
Home-page: https://github.com/Kijewski/pyiced
Author: René Kijewski
Author-email: pypi.org@k6i.de
License: Apache License 2.0
Platform: UNKNOWN
Classifier: Development Status :: 3 - Alpha
Classifier: License :: OSI Approved :: Apache Software License
Classifier: Operating System :: POSIX :: Linux
Classifier: Operating System :: Microsoft :: Windows
Classifier: Programming Language :: Python :: 3
Classifier: Programming Language :: Python :: 3 :: Only
Classifier: Programming Language :: Python :: 3.7
Classifier: Programming Language :: Python :: 3.8
Classifier: Programming Language :: Python :: 3.9
Classifier: Programming Language :: Python :: 3.10
Classifier: Programming Language :: Rust
Classifier: Topic :: Games/Entertainment
Classifier: Topic :: Software Development :: User Interfaces
Requires-Python: <4,>=3.7
License-File: LICENSE.md
